pipeline_sdk_test68/__init__.py
pipeline_sdk_test68/auth_service.py
pipeline_sdk_test68/inference_pipeline.py
pipeline_sdk_test68/model_inference_dsl_component.py
pipeline_sdk_test68/model_train_dsl_component.py
pipeline_sdk_test68/model_validate_dsl_component.py
pipeline_sdk_test68/pipeline_util.py
pipeline_sdk_test68/run_inference_pipeline.py
pipeline_sdk_test68/run_training_pipeline.py
pipeline_sdk_test68/run_validate_pipeline.py
pipeline_sdk_test68/train_pipeline.py
pipeline_sdk_test68/validate_pipeline.py
pipeline_sdk_test68-1.0.0.dist-info/METADATA
pipeline_sdk_test68-1.0.0.dist-info/WHEEL
pipeline_sdk_test68-1.0.0.dist-info/top_level.txt
pipeline_sdk_test68-1.0.0.dist-info/RECORD
